fitzutils/__init__.py
fitzutils/fitzutils.py
pdftocgen/__init__.py
pdftocgen/__main__.py
pdftocgen/app.py
pdftocgen/filter.py
pdftocgen/recipe.py
pdftocgen/tocgen.py
pdftocio/__init__.py
pdftocio/__main__.py
pdftocio/app.py
pdftocio/tocio.py
pdftocio/tocparser.py
pdfxmeta/__init__.py
pdfxmeta/__main__.py
pdfxmeta/app.py
pdfxmeta/pdfxmeta.py
pdf_tocgen-1.3.4.dist-info/LICENSE
pdf_tocgen-1.3.4.dist-info/METADATA
pdf_tocgen-1.3.4.dist-info/WHEEL
pdf_tocgen-1.3.4.dist-info/entry_points.txt
pdf_tocgen-1.3.4.dist-info/RECORD
