Metadata-Version: 2.1
Name: pdf.tocgen
Version: 1.3.4
Summary: Automatically generate table of contents for pdf files
Home-page: https://krasjet.com/voice/pdf.tocgen/
License: GPL-3.0-or-later
Keywords: pdf,cli
Author: krasjet
Requires-Python: >=3.7,<4.0
Classifier: Development Status :: 3 - Alpha
Classifier: Environment :: Console
Classifier: Intended Audience :: End Users/Desktop
Classifier: License :: OSI Approved :: GNU General Public License v3 or later (GPLv3+)
Classifier: Programming Language :: Python :: 3
Classifier: Programming Language :: Python :: 3.7
Classifier: Programming Language :: Python :: 3.8
Classifier: Programming Language :: Python :: 3.9
Classifier: Programming Language :: Python :: 3.10
Classifier: Programming Language :: Python :: 3.11
Classifier: Programming Language :: Python :: 3.12
Requires-Dist: PyMuPDF (>=1.18.14,<2.0.0)
Requires-Dist: chardet (>=5.1.0,<6.0.0)
Requires-Dist: toml (>=0.10.2,<0.11.0)
Project-URL: Repository, https://github.com/Krasjet/pdf.tocgen
